py2to3cov/__init__.py
py2to3cov/__main__.py
py2to3cov/data_model/__init__.py
py2to3cov/data_model/diff_summary.py
py2to3cov/futurizer/__init__.py
py2to3cov/futurizer/refactoring_tool.py
py2to3cov/mgmt/__init__.py
py2to3cov/mgmt/const.py
py2to3cov-0.0.10.dist-info/LICENSE
py2to3cov-0.0.10.dist-info/METADATA
py2to3cov-0.0.10.dist-info/WHEEL
py2to3cov-0.0.10.dist-info/entry_points.txt
py2to3cov-0.0.10.dist-info/top_level.txt
py2to3cov-0.0.10.dist-info/RECORD
