Metadata-Version: 2.1
Name: py2to3cov
Version: 0.0.10
Summary: Python 2/3 compatibility tool. Provide measurements on Python 3 incompatible code similar to coverage reports.
Home-page: https://github.com/do-py-together/py2to3cov
Author: Tim Davis
Author-email: timdavis.3991@gmail.com
License: UNKNOWN
Keywords: development
Platform: UNKNOWN
Classifier: Development Status :: 3 - Alpha
Classifier: Intended Audience :: Developers
Classifier: Topic :: Software Development :: Build Tools
Classifier: Operating System :: OS Independent
Classifier: License :: OSI Approved :: MIT License
Classifier: Programming Language :: Python
Classifier: Programming Language :: Python :: 2
Classifier: Programming Language :: Python :: 2.7
Requires-Dist: argparse (==1.4.0)
Requires-Dist: future (==0.17.1)
Requires-Dist: dominate (==2.6.0)
